PyInstaller/__init__.py
PyInstaller/__main__.py
PyInstaller/_recursion_too_deep_message.py
PyInstaller/_shared_with_waf.py
PyInstaller/compat.py
PyInstaller/config.py
PyInstaller/configure.py
PyInstaller/exceptions.py
PyInstaller/log.py
PyInstaller/archive/__init__.py
PyInstaller/archive/pyz_crypto.py
PyInstaller/archive/readers.py
PyInstaller/archive/writers.py
PyInstaller/bootloader/Linux-64bit-arm/run
PyInstaller/bootloader/Linux-64bit-arm/run_d
PyInstaller/building/__init__.py
PyInstaller/building/api.py
PyInstaller/building/build_main.py
PyInstaller/building/datastruct.py
PyInstaller/building/icon.py
PyInstaller/building/makespec.py
PyInstaller/building/osx.py
PyInstaller/building/splash.py
PyInstaller/building/splash_templates.py
PyInstaller/building/templates.py
PyInstaller/building/utils.py
PyInstaller/depend/__init__.py
PyInstaller/depend/analysis.py
PyInstaller/depend/bindepend.py
PyInstaller/depend/bytecode.py
PyInstaller/depend/dylib.py
PyInstaller/depend/imphook.py
PyInstaller/depend/imphookapi.py
PyInstaller/depend/utils.py
PyInstaller/fake-modules/pyi_splash.py
PyInstaller/fake-modules/_pyi_rth_utils/__init__.py
PyInstaller/fake-modules/_pyi_rth_utils/_win32.py
PyInstaller/fake-modules/_pyi_rth_utils/qt.py
PyInstaller/fake-modules/_pyi_rth_utils/tempfile.py
PyInstaller/hooks/__init__.py
PyInstaller/hooks/hook-PIL.Image.py
PyInstaller/hooks/hook-PIL.ImageFilter.py
PyInstaller/hooks/hook-PIL.SpiderImagePlugin.py
PyInstaller/hooks/hook-PIL.py
PyInstaller/hooks/hook-PyQt5.QAxContainer.py
PyInstaller/hooks/hook-PyQt5.Qsci.py
PyInstaller/hooks/hook-PyQt5.Qt.py
PyInstaller/hooks/hook-PyQt5.Qt3DAnimation.py
PyInstaller/hooks/hook-PyQt5.Qt3DCore.py
PyInstaller/hooks/hook-PyQt5.Qt3DExtras.py
PyInstaller/hooks/hook-PyQt5.Qt3DInput.py
PyInstaller/hooks/hook-PyQt5.Qt3DLogic.py
PyInstaller/hooks/hook-PyQt5.Qt3DRender.py
PyInstaller/hooks/hook-PyQt5.QtBluetooth.py
PyInstaller/hooks/hook-PyQt5.QtChart.py
PyInstaller/hooks/hook-PyQt5.QtCore.py
pyinstaller-6.11.0.dist-info/COPYING.txt
pyinstaller-6.11.0.dist-info/METADATA
pyinstaller-6.11.0.dist-info/WHEEL
pyinstaller-6.11.0.dist-info/entry_points.txt
pyinstaller-6.11.0.dist-info/top_level.txt
pyinstaller-6.11.0.dist-info/RECORD
